nuvla/__init__.py
nuvla/api/__init__.py
nuvla/api/api.py
nuvla/api/models.py
nuvla/api/resources/__init__.py
nuvla/api/resources/base.py
nuvla/api/resources/callback.py
nuvla/api/resources/credential.py
nuvla/api/resources/data.py
nuvla/api/resources/deployment.py
nuvla/api/resources/deployment_parameter.py
nuvla/api/resources/infra_service.py
nuvla/api/resources/module.py
nuvla/api/resources/notification.py
nuvla/api/resources/user.py
nuvla/api/util/__init__.py
nuvla/api/util/date.py
nuvla/api/util/filter.py
nuvla_api-4.2.3.dist-info/LICENSE
nuvla_api-4.2.3.dist-info/METADATA
nuvla_api-4.2.3.dist-info/WHEEL
nuvla_api-4.2.3.dist-info/RECORD
